Metadata-Version: 2.1
Name: onto-tool
Version: 1.8.0
Summary: Ontology Maintenance and Release Tool
Home-page: https://github.com/semanticarts/ontology-toolkit
Author: Boris Pelakh
Author-email: boris.pelakh@semanticarts.com
License: UNKNOWN
Platform: UNKNOWN
Classifier: Development Status :: 5 - Production/Stable
Classifier: Programming Language :: Python :: 3
Classifier: License :: OSI Approved :: Apache Software License
Classifier: Operating System :: OS Independent
Requires-Python: >=3.8
License-File: LICENSE
Requires-Dist: pyparsing ==2.4.7
Requires-Dist: rdflib ~=6.1.1
Requires-Dist: pydot
Requires-Dist: jinja2
Requires-Dist: markdown2
Requires-Dist: pyyaml
Requires-Dist: jsonschema >=3.2.0
Requires-Dist: SPARQLWrapper >=1.8.5
Requires-Dist: pyshacl ~=0.17.0
